merchantapi/__init__.py
merchantapi/abstract.py
merchantapi/authenticator.py
merchantapi/client.py
merchantapi/listquery.py
merchantapi/logging.py
merchantapi/model.py
merchantapi/multicall.py
merchantapi/request.py
merchantapi/response.py
merchantapi/sshagent.py
merchantapi/version.py
merchantapi/model/__init__.py
merchantapi/model/all_order_payment.py
merchantapi/model/attribute_template.py
merchantapi/model/attribute_template_attribute.py
merchantapi/model/attribute_template_option.py
merchantapi/model/attribute_template_product.py
merchantapi/model/availability_group.py
merchantapi/model/availability_group_business_account.py
merchantapi/model/availability_group_category.py
merchantapi/model/availability_group_customer.py
merchantapi/model/availability_group_product.py
merchantapi/model/availability_group_shipping_method.py
merchantapi/model/base_subscription.py
merchantapi/model/branch.py
merchantapi/model/branch_css_resource.py
merchantapi/model/branch_css_resource_version.py
merchantapi/model/branch_item_version.py
merchantapi/model/branch_javascript_resource_version.py
merchantapi/model/branch_page_version.py
merchantapi/model/branch_property_version.py
merchantapi/model/branch_template_version.py
merchantapi/model/business_account.py
merchantapi/model/business_account_customer.py
merchantapi/model/category.py
merchantapi/model/category_product.py
merchantapi/model/changeset.py
merchantapi/model/changeset_change.py
merchantapi/model/changeset_css_resource.py
merchantapi/model/changeset_css_resource_version.py
merchantapi/model/changeset_item_version.py
merchantapi/model/changeset_javascript_resource_version.py
merchantapi/model/changeset_property_version.py
merchantapi/model/changeset_template_version.py
merchantapi/model/child_category.py
merchantapi/model/copy_page_rule.py
merchantapi/model/copy_page_rules_settings.py
merchantapi/model/copy_product_rule.py
merchantapi/model/copy_product_rules_custom_field.py
merchantapi/model/copy_product_rules_module.py
merchantapi-2.7.0.dist-info/LICENSE
merchantapi-2.7.0.dist-info/METADATA
merchantapi-2.7.0.dist-info/WHEEL
merchantapi-2.7.0.dist-info/top_level.txt
merchantapi-2.7.0.dist-info/RECORD
