Metadata-Version: 2.1
Name: merchantapi
Version: 2.7.0
Summary: Miva Merchant JSON API SDK
Home-page: https://www.miva.com
Author: Miva, Inc.
Author-email: support@miva.com
License: Miva SDK License Agreement
Keywords: miva merchant json api sdk
Platform: UNKNOWN
Requires-Python: >=3.6
Requires-Dist: pycryptodome
Requires-Dist: requests
